Metadata-Version: 2.0
Name: odoo9-addon-sale-delivery-block-proc-group-by-line
Version: 9.0.1.0.0
Summary: Module that allows module sale_delivery_block to work with sale_procurement_group_by_line
Home-page: https://github.com/OCA/sale-workflow
Author: Eficent, Odoo Community Association (OCA)
Author-email: support@odoo-community.org
License: AGPL-3
Platform: UNKNOWN
Classifier: Programming Language :: Python :: 2.7
Classifier: Framework :: Odoo
Classifier: License :: OSI Approved :: GNU Affero General Public License v3
Requires-Dist: odoo (<9.1a,>=9.0a)
Requires-Dist: odoo9-addon-sale-delivery-block
Requires-Dist: odoo9-addon-sale-procurement-group-by-line
